coala_quickstart/Constants.py
coala_quickstart/Strings.py
coala_quickstart/__init__.py
coala_quickstart/coala_quickstart.py
coala_quickstart/generation/Bears.py
coala_quickstart/generation/FileGlobs.py
coala_quickstart/generation/InfoCollector.py
coala_quickstart/generation/InfoMapping.py
coala_quickstart/generation/Project.py
coala_quickstart/generation/Settings.py
coala_quickstart/generation/SettingsFilling.py
coala_quickstart/generation/Utilities.py
coala_quickstart/generation/__init__.py
coala_quickstart/info_extraction/Info.py
coala_quickstart/info_extraction/InfoExtractor.py
coala_quickstart/info_extraction/InfoScope.py
coala_quickstart/info_extraction/Information.py
coala_quickstart/info_extraction/Utilities.py
coala_quickstart/info_extraction/__init__.py
coala_quickstart/info_extractors/EditorconfigInfoExtractor.py
coala_quickstart/info_extractors/EditorconfigParsing.py
coala_quickstart/info_extractors/GemfileInfoExtractor.py
coala_quickstart/info_extractors/GruntfileInfoExtractor.py
coala_quickstart/info_extractors/PackageJSONInfoExtractor.py
coala_quickstart/info_extractors/Utilities.py
coala_quickstart/info_extractors/__init__.py
coala_quickstart/interaction/Logo.py
coala_quickstart/interaction/__init__.py
coala_quickstart-0.4.0.dist-info/DESCRIPTION.rst
coala_quickstart-0.4.0.dist-info/METADATA
coala_quickstart-0.4.0.dist-info/RECORD
coala_quickstart-0.4.0.dist-info/WHEEL
coala_quickstart-0.4.0.dist-info/entry_points.txt
coala_quickstart-0.4.0.dist-info/metadata.json
coala_quickstart-0.4.0.dist-info/top_level.txt
tests/TestUtilities.py
tests/__init__.py
tests/generation/Bears.py
tests/generation/FileGlobs.py
tests/generation/InfoCollectorTest.py
tests/generation/Project.py
tests/generation/SettingsFillingTest.py
tests/generation/SettingsTest.py
tests/generation/__init__.py
tests/info_extraction/InfoExtractorTest.py
tests/info_extraction/InfoScopeTest.py
tests/info_extraction/InfoTest.py
tests/info_extraction/__init__.py
tests/interaction/Logo.py
tests/interaction/__init__.py
tests/test_bears/DependentBear.py
tests/test_bears/LanguageSettingBear.py
tests/test_bears/NonOptionalSettingBear.py
tests/test_bears/SmellCapabilityBear.py
tests/test_bears/SomeLinterBear.py
tests/test_bears/SpaceConsistencyTestBear.py
